filter/mean/mean_filter.v
module mean_filter(
    input clk,
    input rst_n,

    input en_i,
    input [7:0] data_i,
    output reg [7:0] data_o,
    output reg done_o
);

//-----------------------------------------------------------------
reg [7:0] max, min;
reg [11:0] sum;
reg [3:0] num;

always @(posedge clk or negedge rst_n) begin
    if (!rst_n) begin
        sum <= 8'd0;
    end else if (en_i) begin
        sum <= sum + data_i;       
    end else begin
        sum <= 8'd0;
    end       
end

always @(posedge clk or negedge rst_n) begin
    if (!rst_n) begin
        min <= 8'hff;
    end else if (en_i) begin
        if (data_i < min) 
            min <= data_i;
    end else begin
        min <= 8'hff;
    end     
end

always @(posedge clk or negedge rst_n) begin
    if (!rst_n) begin
        max <= 8'h00;
    end else if (en_i) begin
        if (max < data_i) 
            max <= data_i;
    end else begin
        max <= 8'h00;
    end     
end

always @(posedge clk or negedge rst_n) begin
    if (!rst_n) begin
        num <= 8'h00;
    end else if (en_i) begin
        if (num == 4'd10)
            num <= 4'd0;
        else
            num <= num + 4'd1;
    end else begin
        num <= 4'd0;
    end
end 

always @(posedge clk or negedge rst_n) begin
    if (!rst_n) begin
        data_o <= 8'd0;
        done_o <= 1'd0;
    end else if (en_i) begin
        if (num == 4'd10) begin
            data_o <= (sum - max - min) >> 3;
            done_o <= 1'd1;
        end else begin
            data_o <= 8'd0;
            done_o <= 1'd0;
        end
    end else begin
        data_o <= 8'd0;
        done_o <= 1'd0;
    end
end
endmodule

filter/mean/mean_filter_tb.v
`timescale 1ps/1ps

`define clk_period 20

module mean_filter_tb();

reg clk, rst_n;

reg en_i;
reg [7:0] data_i;

wire [7:0] data_o;
wire done;

mean_filter MEAN_FILTER(
    .clk(clk),
    .rst_n(rst_n),
    
    .en_i(en_i),
    .data_i(data_i),
    .data_o(data_o),
    .done_o(done_o)
);

initial begin
    clk = 1'b1;
end

always #(`clk_period/2) clk = ~clk;

integer i = 0;

initial begin
    $dumpfile("mean_filter_wave.vcd");
    $dumpvars(0, mean_filter_tb);

    rst_n   = 1'b0;
    en_i    = 1'b0;
    data_i  = 8'd0;

    #(`clk_period);
    rst_n   = 1'b1;

    #(`clk_period);
    en_i    = 1'b1;

    for (i = 0; i < 10; i = i + 1) begin
        data_i = data_i + 8'd1;
        #(`clk_period);
    end

    data_i = 8'd0;
    #(`clk_period);

    en_i    = 1'b0;
    #(`clk_period * 10);

    $finish;
end

endmodule

filter/mean/mean_filter_wave.vcd
$date
	Fri Jul 15 14:56:30 2022
$end
$version
	Icarus Verilog
$end
$timescale
	1ps
$end
$scope module mean_filter_tb $end
$var wire 1 ! done_o $end
$var wire 8 " data_o [7:0] $end
$var reg 1 # clk $end
$var reg 8 $ data_i [7:0] $end
$var reg 1 % en_i $end
$var reg 1 & rst_n $end
$var integer 32 ' i [31:0] $end
$scope module MEAN_FILTER $end
$var wire 1 # clk $end
$var wire 8 ( data_i [7:0] $end
$var wire 1 % en_i $end
$var wire 1 & rst_n $end
$var reg 8 ) data_o [7:0] $end
$var reg 1 ! done_o $end
$var reg 8 * max [7:0] $end
$var reg 8 + min [7:0] $end
$var reg 4 , num [3:0] $end
$var reg 12 - sum [11:0] $end
$upscope $end
$upscope $end
$enddefinitions $end
#0
$dumpvars
b0 -
b0 ,
b11111111 +
b0 *
b0 )
b0 (
b0 '
0&
0%
b0 $
1#
b0 "
0!
$end
#10
0#
#20
1#
1&
#30
0#
#40
b1 -
b1 +
b1 *
b1 ,
1#
b1 $
b1 (
1%
#50
0#
#60
b10 ,
b10 *
b11 -
1#
b10 $
b10 (
b1 '
#70
0#
#80
b110 -
b11 *
b11 ,
1#
b11 $
b11 (
b10 '
#90
0#
#100
b100 ,
b100 *
b1010 -
1#
b100 $
b100 (
b11 '
#110
0#
#120
b1111 -
b101 *
b101 ,
1#
b101 $
b101 (
b100 '
#130
0#
#140
b110 ,
b110 *
b10101 -
1#
b110 $
b110 (
b101 '
#150
0#
#160
b11100 -
b111 *
b111 ,
1#
b111 $
b111 (
b110 '
#170
0#
#180
b1000 ,
b1000 *
b100100 -
1#
b1000 $
b1000 (
b111 '
#190
0#
#200
b101101 -
b1001 *
b1001 ,
1#
b1001 $
b1001 (
b1000 '
#210
0#
#220
b1010 ,
b1010 *
b110111 -
1#
b1010 $
b1010 (
b1001 '
#230
0#
#240
b0 +
b0 ,
1!
b101 "
b101 )
1#
b0 $
b0 (
b1010 '
#250
0#
#260
0!
b0 "
b0 )
b0 *
b11111111 +
b0 -
1#
0%
