filter/gaussian/gaussian_filter.v
module gaussian_filter(
    input clk,
    input rst_n,

    input en_i,
    input [7:0] d1_i,
    input [7:0] d2_i,
    input [7:0] d3_i,

    output reg done_o,
    output reg [7:0] gaussian_o
);

reg [7:0] d11, d12, d13;
reg [7:0] d21, d22, d23;
reg [7:0] d31, d32, d33;

reg [11:0] gs1, gs2, gs3, gs_sum;

reg flow;
reg [3:0] count;

always @(posedge clk or negedge rst_n) begin
    if (!rst_n) begin
        d11     <= 8'd0;
        d12     <= 8'd0;
        d13     <= 8'd0;
    end else begin
        d11     <= d1_i;
        d12     <= d11;
        d13     <= d12;
    end
end

always @(posedge clk or negedge rst_n) begin
    if (!rst_n) begin
        d21     <= 8'd0;
        d22     <= 8'd0;
        d23     <= 8'd0;
    end else begin
        d21     <= d2_i;
        d22     <= d21;
        d23     <= d22;
    end
end

always @(posedge clk or negedge rst_n) begin
    if (!rst_n) begin
        d31     <= 8'd0;
        d32     <= 8'd0;
        d33     <= 8'd0;
    end else begin
        d31     <= d3_i;
        d32     <= d31;
        d33     <= d32;
    end
end

always @(posedge clk or negedge rst_n) begin
    if (!rst_n) begin
        gs1     <= 12'd0;
        gs2     <= 12'd0;
        gs3     <= 12'd0;
    end else begin
        gs1     <= d11   + d12*2 + d13;
        gs2     <= d21*2 + d22*4 + d23*2;
        gs3     <= d31   + d32*2 + d33;
    end 
end

always @(posedge clk or negedge rst_n) begin
    if (!rst_n) begin
        gs_sum  <= 12'd0;
    end else begin
        gs_sum  <= gs1 + gs2 + gs3;
    end
end

always @(posedge clk or negedge rst_n) begin
    if (!rst_n) begin
        gaussian_o  <= 8'd0;
    end else begin
        gaussian_o  <= gs_sum >> 4;
    end
end

always @(posedge clk or negedge rst_n) begin
    if (!rst_n) begin
        flow    <= 1'd0;
        count   <= 4'd0;
        done_o  <= 1'd0;
    end else begin
        case (flow)
            1'd0:
                begin
                    done_o  <= 1'd0;
                    if (en_i) begin
                        flow <= 1'd1;
                        count <= count + 4'd1;
                    end
                end 

            1'd1:
                if (count == 4'd5) begin
                    flow <= 1'd0;
                    count <= 4'd0;
                    done_o <= 1'd1;
                end else begin
                    count <= count + 4'd1;
                end

            default:
                begin
                    flow    <= 1'd0;
                    count   <= 4'd0;
                    done_o  <= 1'd0;
                end
        endcase
    end
end
endmodule

filter/gaussian/gaussian_filter_tb.v
`timescale 1ns/1ps

`define clk_period 20

module gaussian_filter_tb();

    reg clk, rst_n;

    reg en_i;
    reg [7:0] d1_i, d2_i, d3_i;

    wire done_o;
    wire [7:0] gaussian_o;

    gaussian_filter Ggaussian_FILTER(
        .clk(clk),
        .rst_n(rst_n),

        .en_i(en_i),
        .d1_i(d1_i),
        .d2_i(d2_i),
        .d3_i(d3_i),

        .done_o(done_o),
        .gaussian_o(gaussian_o)
    );

    initial begin
        clk = 1'b1;
        $dumpfile("gaussian_filter.vcd");
        $dumpvars(0, gaussian_filter_tb);
    end

    always #(`clk_period/2) clk = ~clk;

    initial begin
        rst_n   = 1'b0;
        en_i    = 1'b0;
        d1_i    = 8'd0;
        d2_i    = 8'd0;
        d3_i    = 8'd0;

        @(negedge clk);
        rst_n   = 1'b1;

        @(negedge clk);
        en_i    = 1'b1;
        d1_i    = 8'd1;
        d2_i    = 8'd2;
        d3_i    = 8'd3;

        @(negedge clk);
        en_i    = 1'b0;
        d1_i    = 8'd4;
        d2_i    = 8'd5;
        d3_i    = 8'd6;

        @(negedge clk);
        d1_i    = 8'd7;
        d2_i    = 8'd8;
        d3_i    = 8'd9;

        repeat(20) @(posedge clk);

        $finish;
    end
endmodule

filter/gaussian/gaussian_filter.vcd
$date
	Sat Jul 16 17:28:36 2022
$end
$version
	Icarus Verilog
$end
$timescale
	1ps
$end
$scope module gaussian_filter_tb $end
$var wire 8 ! gaussian_o [7:0] $end
$var wire 1 " done_o $end
$var reg 1 # clk $end
$var reg 8 $ d1_i [7:0] $end
$var reg 8 % d2_i [7:0] $end
$var reg 8 & d3_i [7:0] $end
$var reg 1 ' en_i $end
$var reg 1 ( rst_n $end
$scope module Ggaussian_FILTER $end
$var wire 1 # clk $end
$var wire 8 ) d1_i [7:0] $end
$var wire 8 * d2_i [7:0] $end
$var wire 8 + d3_i [7:0] $end
$var wire 1 ' en_i $end
$var wire 1 ( rst_n $end
$var reg 4 , count [3:0] $end
$var reg 8 - d11 [7:0] $end
$var reg 8 . d12 [7:0] $end
$var reg 8 / d13 [7:0] $end
$var reg 8 0 d21 [7:0] $end
$var reg 8 1 d22 [7:0] $end
$var reg 8 2 d23 [7:0] $end
$var reg 8 3 d31 [7:0] $end
$var reg 8 4 d32 [7:0] $end
$var reg 8 5 d33 [7:0] $end
$var reg 1 " done_o $end
$var reg 1 6 flow $end
$var reg 8 7 gaussian_o [7:0] $end
$var reg 12 8 gs1 [11:0] $end
$var reg 12 9 gs2 [11:0] $end
$var reg 12 : gs3 [11:0] $end
$var reg 12 ; gs_sum [11:0] $end
$upscope $end
$upscope $end
$enddefinitions $end
#0
$dumpvars
b0 ;
b0 :
b0 9
b0 8
b0 7
06
b0 5
b0 4
b0 3
b0 2
b0 1
b0 0
b0 /
b0 .
b0 -
b0 ,
b0 +
b0 *
b0 )
0(
0'
b0 &
b0 %
b0 $
1#
0"
b0 !
$end
#10000
1(
0#
#20000
1#
#30000
b11 &
b11 +
b10 %
b10 *
b1 $
b1 )
1'
0#
#40000
b1 -
b10 0
b11 3
b1 ,
16
1#
#50000
b110 &
b110 +
b101 %
b101 *
b100 $
b100 )
0'
0#
#60000
b10 ,
b11 :
b100 9
b1 8
b11 4
b110 3
b10 1
b101 0
b1 .
b100 -
1#
#70000
b1001 &
b1001 +
b1000 %
b1000 *
b111 $
b111 )
0#
#80000
b1 /
b100 .
b111 -
b10 2
b101 1
b1000 0
b11 5
b110 4
b1001 3
b1100 :
b10010 9
b110 8
b1000 ;
b11 ,
1#
#90000
0#
#100000
b100 ,
b100100 ;
b11000 :
b101000 9
b10000 8
b110 5
b1001 4
b101 2
b1000 1
b100 /
b111 .
1#
#110000
0#
#120000
b111 /
b1000 2
b1001 5
b100001 :
b111010 9
b11001 8
b1010000 ;
b10 !
b10 7
b101 ,
1#
#130000
0#
#140000
1"
b0 ,
06
b101 !
b101 7
b1110100 ;
b100100 :
b1000000 9
b11100 8
1#
#150000
0#
#160000
b10000000 ;
b111 !
b111 7
0"
1#
#170000
0#
#180000
b1000 !
b1000 7
1#
