filter/median/sort.v
module sort(
    input clk,
    input rst_n,

    input [7:0] d1_i,
    input [7:0] d2_i,
    input [7:0] d3_i,

    output reg [7:0] max_o,
    output reg [7:0] med_o,
    output reg [7:0] min_o
);

always @(posedge clk or negedge rst_n) begin
    if (!rst_n)
        max_o   <= 8'd0;
    else if (d1_i >= d2_i && d1_i >= d3_i) 
        max_o   <= d1_i;
    else if (d2_i >= d1_i && d2_i >= d3_i)
        max_o   <= d2_i;
    else if (d3_i >= d1_i && d3_i >= d1_i)
        max_o   <= d3_i;
end

always @(posedge clk or negedge rst_n) begin
    if (!rst_n)
        med_o   <= 8'd0;
    else if ((d1_i >= d2_i && d1_i <= d3_i) || (d1_i >= d3_i && d1_i <= d2_i)) 
        med_o   <= d1_i;
    else if ((d2_i >= d1_i && d2_i <= d3_i) || (d2_i >= d3_i && d2_i <= d1_i))
        med_o   <= d2_i;
    else if ((d3_i >= d1_i && d3_i <= d2_i) || (d3_i >= d2_i && d3_i <= d1_i))       
        med_o   <= d3_i;
end

always @(posedge clk or negedge rst_n) begin
    if (!rst_n)
        min_o   <= 8'd0;
    else if (d1_i <= d2_i && d1_i <= d3_i) 
        min_o   <= d1_i;
    else if (d2_i <= d1_i && d2_i <= d3_i)
        min_o   <= d2_i;
    else if (d3_i <= d1_i && d3_i <= d2_i)
        min_o   <= d3_i;
end
endmodule

filter/median/median_filter.v
module median_filter(
    input clk,
    input rst_n,

    input en_i,
    input [7:0] d1_i,
    input [7:0] d2_i,
    input [7:0] d3_i,

    output reg done_o,
    output [7:0] median_o
);

reg [7:0] d11, d12, d13;
reg [7:0] d21, d22, d23;
reg [7:0] d31, d32, d33;

wire [7:0] max1, med1, min1;
wire [7:0] max2, med2, min2;
wire [7:0] max3, med3, min3;

wire [7:0] min_of_max, med_of_med, max_of_min;

reg flow;
reg [3:0] count;

always @(posedge clk or negedge rst_n) begin
    if (!rst_n) begin
        d11     <= 8'd0;
        d12     <= 8'd0;
        d13     <= 8'd0;
    end else begin
        d11     <= d1_i;
        d12     <= d11;
        d13     <= d12;
    end
end

always @(posedge clk or negedge rst_n) begin
    if (!rst_n) begin
        d21     <= 8'd0;
        d22     <= 8'd0;
        d23     <= 8'd0;
    end else begin
        d21     <= d2_i;
        d22     <= d21;
        d23     <= d22;
    end
end

always @(posedge clk or negedge rst_n) begin
    if (!rst_n) begin
        d31     <= 8'd0;
        d32     <= 8'd0;
        d33     <= 8'd0;
    end else begin
        d31     <= d3_i;
        d32     <= d31;
        d33     <= d32;
    end
end

sort SORT_LINE1_DATA(
    .clk(clk),
    .rst_n(rst_n),
    
    .d1_i(d11),
    .d2_i(d12),
    .d3_i(d13),

    .max_o(max1),
    .med_o(med1),
    .min_o(min1)
);

sort SORT_LINE2_DATA(
    .clk(clk),
    .rst_n(rst_n),
    
    .d1_i(d21),
    .d2_i(d22),
    .d3_i(d23),

    .max_o(max2),
    .med_o(med2),
    .min_o(min2)
);

sort SORT_LINE3_DATA(
    .clk(clk),
    .rst_n(rst_n),
    
    .d1_i(d31),
    .d2_i(d32),
    .d3_i(d33),

    .max_o(max3),
    .med_o(med3),
    .min_o(min3)
);

sort SORT_MAX_DATA(
    .clk(clk),
    .rst_n(rst_n),

    .d1_i(max1),
    .d2_i(max2),
    .d3_i(max3),

    .max_o(),
    .med_o(),
    .min_o(min_of_max)
);

sort SORT_MED_DATA(
    .clk(clk),
    .rst_n(rst_n),

    .d1_i(med1),
    .d2_i(med2),
    .d3_i(med3),

    .max_o(),
    .med_o(med_of_med),
    .min_o()
);

sort SORT_MIN_DATA(
    .clk(clk),
    .rst_n(rst_n),

    .d1_i(min1),
    .d2_i(min2),
    .d3_i(min3),

    .max_o(max_of_min),
    .med_o(),
    .min_o()
);

sort SORT_FINAL_DATA(
    .clk(clk),
    .rst_n(rst_n),

    .d1_i(min_of_max),
    .d2_i(med_of_med),
    .d3_i(max_of_min),

    .max_o(),
    .med_o(median_o),
    .min_o()
);

always @(posedge clk or negedge rst_n) begin
    if (!rst_n) begin
        flow    <= 1'd0;
        count   <= 4'd0;
        done_o  <= 1'd0;
    end else begin
        case (flow)
            1'd0:
                begin
                    done_o  <= 1'd0;
                    if (en_i) begin
                        flow <= 1'd1;
                        count <= count + 4'd1;
                    end
                end 

            1'd1:
                if (count == 4'd5) begin
                    flow <= 1'd0;
                    count <= 4'd0;
                    done_o <= 1'd1;
                end else begin
                    count <= count + 4'd1;
                end

            default:
                begin
                    flow <= 1'd0;
                    count <= 4'd0;
                    done_o <= 1'd0;
                end
        endcase
    end
end
endmodule

filter/median/median_filter_tb.v
`timescale 1ns/1ps

`define clk_period 20

module median_filter_tb();

reg clk, rst_n;

reg en_i;
reg [7:0] d1_i, d2_i, d3_i;

wire done_o;
wire [7:0] median_o;

median_filter MEDIAN_FILTER(
    .clk(clk),
    .rst_n(rst_n),

    .en_i(en_i),
    .d1_i(d1_i),
    .d2_i(d2_i),
    .d3_i(d3_i),

    .done_o(done_o),
    .median_o(median_o)
);

initial begin
    clk = 1'b1;
    $dumpfile("median_wave.vcd");
    $dumpvars(0, median_filter_tb);
end

always #(`clk_period/2) clk = ~clk;


initial begin
    rst_n   = 1'd0;
    en_i    = 1'b0;
    d1_i    = 8'd0;
    d2_i    = 8'd0;
    d3_i    = 8'd0;

    @(posedge clk);
    rst_n   = 1'b1;

    @(posedge clk);
    #2 en_i    = 1'b1;
     d1_i    = 8'd1;
     d2_i    = 8'd2;
     d3_i    = 8'd3;
    
    @(posedge clk);
    #2 en_i    = 1'b0;
     d1_i    = 8'd4;
     d2_i    = 8'd5;
     d3_i    = 8'd6;

    @(posedge clk);
    #2 d1_i    = 8'd7;
     d2_i    = 8'd8;
     d3_i    = 8'd9;

    repeat(20) @(posedge clk);

    $finish; 
end
















endmodule

filter/median/median_wave.vcd
$date
	Fri Jul 15 21:34:58 2022
$end
$version
	Icarus Verilog
$end
$timescale
	1ps
$end
$scope module median_filter_tb $end
$var wire 8 ! median_o [7:0] $end
$var wire 1 " done_o $end
$var reg 1 # clk $end
$var reg 8 $ d1_i [7:0] $end
$var reg 8 % d2_i [7:0] $end
$var reg 8 & d3_i [7:0] $end
$var reg 1 ' en_i $end
$var reg 1 ( rst_n $end
$scope module MEDIAN_FILTER $end
$var wire 1 # clk $end
$var wire 8 ) d1_i [7:0] $end
$var wire 8 * d2_i [7:0] $end
$var wire 8 + d3_i [7:0] $end
$var wire 1 ' en_i $end
$var wire 1 ( rst_n $end
$var wire 8 , min_of_max [7:0] $end
$var wire 8 - min3 [7:0] $end
$var wire 8 . min2 [7:0] $end
$var wire 8 / min1 [7:0] $end
$var wire 8 0 median_o [7:0] $end
$var wire 8 1 med_of_med [7:0] $end
$var wire 8 2 med3 [7:0] $end
$var wire 8 3 med2 [7:0] $end
$var wire 8 4 med1 [7:0] $end
$var wire 8 5 max_of_min [7:0] $end
$var wire 8 6 max3 [7:0] $end
$var wire 8 7 max2 [7:0] $end
$var wire 8 8 max1 [7:0] $end
$var reg 4 9 count [3:0] $end
$var reg 8 : d11 [7:0] $end
$var reg 8 ; d12 [7:0] $end
$var reg 8 < d13 [7:0] $end
$var reg 8 = d21 [7:0] $end
$var reg 8 > d22 [7:0] $end
$var reg 8 ? d23 [7:0] $end
$var reg 8 @ d31 [7:0] $end
$var reg 8 A d32 [7:0] $end
$var reg 8 B d33 [7:0] $end
$var reg 1 " done_o $end
$var reg 1 C flow $end
$scope module SORT_FINAL_DATA $end
$var wire 1 # clk $end
$var wire 1 ( rst_n $end
$var wire 8 D d3_i [7:0] $end
$var wire 8 E d2_i [7:0] $end
$var wire 8 F d1_i [7:0] $end
$var reg 8 G max_o [7:0] $end
$var reg 8 H med_o [7:0] $end
$var reg 8 I min_o [7:0] $end
$upscope $end
$scope module SORT_LINE1_DATA $end
$var wire 1 # clk $end
$var wire 8 J d1_i [7:0] $end
$var wire 8 K d2_i [7:0] $end
$var wire 8 L d3_i [7:0] $end
$var wire 1 ( rst_n $end
$var reg 8 M max_o [7:0] $end
$var reg 8 N med_o [7:0] $end
$var reg 8 O min_o [7:0] $end
$upscope $end
$scope module SORT_LINE2_DATA $end
$var wire 1 # clk $end
$var wire 8 P d1_i [7:0] $end
$var wire 8 Q d2_i [7:0] $end
$var wire 8 R d3_i [7:0] $end
$var wire 1 ( rst_n $end
$var reg 8 S max_o [7:0] $end
$var reg 8 T med_o [7:0] $end
$var reg 8 U min_o [7:0] $end
$upscope $end
$scope module SORT_LINE3_DATA $end
$var wire 1 # clk $end
$var wire 8 V d1_i [7:0] $end
$var wire 8 W d2_i [7:0] $end
$var wire 8 X d3_i [7:0] $end
$var wire 1 ( rst_n $end
$var reg 8 Y max_o [7:0] $end
$var reg 8 Z med_o [7:0] $end
$var reg 8 [ min_o [7:0] $end
$upscope $end
$scope module SORT_MAX_DATA $end
$var wire 1 # clk $end
$var wire 8 \ d1_i [7:0] $end
$var wire 8 ] d2_i [7:0] $end
$var wire 8 ^ d3_i [7:0] $end
$var wire 1 ( rst_n $end
$var reg 8 _ max_o [7:0] $end
$var reg 8 ` med_o [7:0] $end
$var reg 8 a min_o [7:0] $end
$upscope $end
$scope module SORT_MED_DATA $end
$var wire 1 # clk $end
$var wire 8 b d1_i [7:0] $end
$var wire 8 c d2_i [7:0] $end
$var wire 8 d d3_i [7:0] $end
$var wire 1 ( rst_n $end
$var reg 8 e max_o [7:0] $end
$var reg 8 f med_o [7:0] $end
$var reg 8 g min_o [7:0] $end
$upscope $end
$scope module SORT_MIN_DATA $end
$var wire 1 # clk $end
$var wire 8 h d1_i [7:0] $end
$var wire 8 i d2_i [7:0] $end
$var wire 8 j d3_i [7:0] $end
$var wire 1 ( rst_n $end
$var reg 8 k max_o [7:0] $end
$var reg 8 l med_o [7:0] $end
$var reg 8 m min_o [7:0] $end
$upscope $end
$upscope $end
$upscope $end
$enddefinitions $end
#0
$dumpvars
b0 m
b0 l
b0 k
b0 j
b0 i
b0 h
b0 g
b0 f
b0 e
b0 d
b0 c
b0 b
b0 a
b0 `
b0 _
b0 ^
b0 ]
b0 \
b0 [
b0 Z
b0 Y
b0 X
b0 W
b0 V
b0 U
b0 T
b0 S
b0 R
b0 Q
b0 P
b0 O
b0 N
b0 M
b0 L
b0 K
b0 J
b0 I
b0 H
b0 G
b0 F
b0 E
b0 D
0C
b0 B
b0 A
b0 @
b0 ?
b0 >
b0 =
b0 <
b0 ;
b0 :
b0 9
b0 8
b0 7
b0 6
b0 5
b0 4
b0 3
b0 2
b0 1
b0 0
b0 /
b0 .
b0 -
b0 ,
b0 +
b0 *
b0 )
0(
0'
b0 &
b0 %
b0 $
1#
0"
b0 !
$end
#10000
0#
#20000
1(
1#
#30000
0#
#40000
1#
#42000
b11 &
b11 +
b10 %
b10 *
b1 $
b1 )
1'
#50000
0#
#60000
b1 9
1C
b11 @
b11 V
b10 =
b10 P
b1 :
b1 J
1#
#62000
b110 &
b110 +
b101 %
b101 *
b100 $
b100 )
0'
#70000
0#
#80000
b1 8
b1 M
b1 \
b10 7
b10 S
b10 ]
b11 6
b11 Y
b11 ^
b1 ;
b1 K
b100 :
b100 J
b10 >
b10 Q
b101 =
b101 P
b11 A
b11 W
b110 @
b110 V
b10 9
1#
#82000
b1001 &
b1001 +
b1000 %
b1000 *
b111 $
b111 )
#90000
0#
#100000
b11 9
b11 B
b11 X
b110 A
b110 W
b1001 @
b1001 V
b10 ?
b10 R
b101 >
b101 Q
b1000 =
b1000 P
b1 <
b1 L
b100 ;
b100 K
b111 :
b111 J
b1 ,
b1 F
b1 a
b10 `
b11 _
b11 2
b11 Z
b11 d
b110 6
b110 Y
b110 ^
b10 3
b10 T
b10 c
b101 7
b101 S
b101 ]
b1 4
b1 N
b1 b
b100 8
b100 M
b100 \
1#
#110000
0#
#120000
b111 8
b111 M
b111 \
b100 4
b100 N
b100 b
b1 /
b1 O
b1 h
b1000 7
b1000 S
b1000 ]
b101 3
b101 T
b101 c
b10 .
b10 U
b10 i
b1001 6
b1001 Y
b1001 ^
b110 2
b110 Z
b110 d
b11 -
b11 [
b11 j
b110 _
b101 `
b100 ,
b100 F
b100 a
b11 e
b10 1
b10 E
b10 f
b1 g
b1 G
b100 <
b100 L
b111 ;
b111 K
b101 ?
b101 R
b1000 >
b1000 Q
b110 B
b110 X
b1001 A
b1001 W
b100 9
1#
#130000
0#
#140000
b101 9
b1001 B
b1001 X
b1000 ?
b1000 R
b111 <
b111 L
b10 !
b10 0
b10 H
b100 G
b1 m
b10 l
b11 5
b11 D
b11 k
b100 g
b101 1
b101 E
b101 f
b110 e
b111 ,
b111 F
b111 a
b1000 `
b1001 _
b110 -
b110 [
b110 j
b1001 2
b1001 Z
b1001 d
b101 .
b101 U
b101 i
b1000 3
b1000 T
b1000 c
b100 /
b100 O
b100 h
b111 4
b111 N
b111 b
1#
#150000
0#
#160000
b111 /
b111 O
b111 h
b1000 .
b1000 U
b1000 i
b1001 -
b1001 [
b1001 j
b1001 e
b1000 1
b1000 E
b1000 f
b111 g
b110 5
b110 D
b110 k
b101 l
b100 m
b111 G
b101 !
b101 0
b101 H
b11 I
1"
b0 9
0C
1#
#170000
0#
#180000
0"
b110 I
b111 !
b111 0
b111 H
b1000 G
b111 m
b1000 l
b1001 5
b1001 D
b1001 k
1#
#190000
0#
#200000
b1001 G
b1000 !
b1000 0
b1000 H
b111 I
1#
